[
   {
      "artist" : "うまるつふり",
      "comment" : "超高速階段、ソフランあり",
      "level" : "11",
      "md5" : "09245bc4b7ec0aae5abd695b5898bc27",
      "proposer" : "スノート",
      "proposerLr2id" : 86393,
      "sha256" : "5ef51c7baf2d71f52cd931bef3938ec9eb9874ce71199ea126871e644ccf370a",
      "submission" : 733,
      "title" : "黒鳶～こくえん～ [元禄模様]",
      "url" : "https://wumalutsufuri.wixsite.com/wumalutsufuri/bms",
      "url_diff" : "",
      "voteNeutral" : 2,
      "voteNo" : 1,
      "votePercent" : "60.00",
      "voteYes" : 2
   },
   {
      "artist" : "天音 / BGA:Johnny obj:小宮千尋大好き差分協会",
      "comment" : "乱打 sl4~5",
      "level" : "4",
      "md5" : "0957a43c8b830d1930c29bee63fc1a14",
      "proposer" : "nono22",
      "proposerLr2id" : 122934,
      "sha256" : "a54b6a8eb9339951f60353ca56b4ab20614e43f74787e07d511c308f8eb7a6c5",
      "submission" : 735,
      "title" : "u gotta party [Viva La Vida!]",
      "url" : "http://manbow.nothing.sh/event/event.cgi?action=More_def&num=179&event=83",
      "url_diff" : "http://beatkim.web.fc2.com",
      "voteNeutral" : 0,
      "voteNo" : 0,
      "votePercent" : "100.00",
      "voteYes" : 3
   },
   {
      "artist" : "Hendrex / obj: Lennon",
      "comment" : "satellite入門にgood",
      "level" : "0",
      "md5" : "0a3c046f60b71eb86731cb75173a0d5b",
      "proposer" : "OXYGEN",
      "proposerLr2id" : 133294,
      "sha256" : "9c9bcf97498f190a3ac254e8d0c8731f268f9d6fefa9c54b2280f8847cbfc14c",
      "submission" : 713,
      "title" : "lightsphere -ほしをみるひと-",
      "url" : "http://uploader.bms.ms/data/bof2009/fixesaraven/hendrex-lightsphere.zip",
      "url_diff" : "https://bmscharteditorsgroup.wixsite.com/initialatoz",
      "voteNeutral" : 4,
      "voteNo" : 0,
      "votePercent" : "77.78",
      "voteYes" : 5
   },
   {
      "artist" : "ルゼ / obj:Lennon",
      "comment" : "▼17 皿複合、微縦連、ラスト微回復",
      "level" : "11",
      "md5" : "166c4a11b18268d2b39a7ac88a1bcc74",
      "proposer" : "姫川友紀",
      "proposerLr2id" : 125835,
      "sha256" : "08f477d43e9969e10d6640a9503299565eae5c8a7437adcb6d237a954e6cdc5a",
      "submission" : 736,
      "title" : "Titanomaquia [ZEUS]",
      "url" : "http://manbow.nothing.sh/event/event.cgi?action=More_def&num=330&event=110",
      "url_diff" : "http://gnqg.rosx.net/upload/upload.cgi?get=00065",
      "voteNeutral" : 1,
      "voteNo" : 0,
      "votePercent" : "83.33",
      "voteYes" : 2
   },
   {
      "artist" : "Sakamiya feat.A.Dokuga img:HalHAL Lyrics:uoru",
      "level" : "2",
      "md5" : "1ace23f0af5a53d1d9fdbe1c6a521661",
      "proposer" : "selene.",
      "proposerLr2id" : 84521,
      "sha256" : "aa90489a2668217fb12ee40dcf211317d634d1b6c0643dd4aa3385ad34043fbb",
      "submission" : 656,
      "title" : "Epic Bellum -universum- [BlackAnother]",
      "url" : "http://manbow.nothing.sh/event/event.cgi?action=More_def&num=258&event=110",
      "url_diff" : "",
      "voteNeutral" : 3,
      "voteNo" : 2,
      "votePercent" : "73.08",
      "voteYes" : 8
   },
   {
      "artist" : "suki / movie:t / obj:NASA",
      "comment" : "ズレ、同時押し",
      "level" : "3",
      "md5" : "1c7b5cd5c32ff6ff9253ea612fbd0a8a",
      "proposer" : "なさ式",
      "proposerLr2id" : 108918,
      "sha256" : "3528ed864f7248c40291947fbcfd2a9ae2c9f7208a649fb35219d980ac198de6",
      "submission" : 698,
      "title" : "テーマソング [NASATHER]",
      "url" : "http://manbow.nothing.sh/event/event.cgi?action=More_def&num=12&event=108",
      "url_diff" : "http://nasashiki.web.fc2.com/hakkyoi.html",
      "voteNeutral" : 2,
      "voteNo" : 3,
      "votePercent" : "66.67",
      "voteYes" : 7
   },
   {
      "artist" : "Arch/movie: Reku obj. DK",
      "level" : "2",
      "md5" : "1f6c0e55e9ef55751b5262619a839dd3",
      "proposer" : "DK",
      "proposerLr2id" : 46697,
      "sha256" : "919c0793bf90dd66f756ffec0dd277863704c13b5411062871e9c83d40c00560",
      "submission" : 730,
      "title" : "fragile crystal [Amethyst]",
      "url" : "http://manbow.nothing.sh/event/event.cgi?action=More_def&num=15&event=87",
      "url_diff" : "http://gnqg.rosx.net/upload/upload.cgi?get=02774",
      "voteNeutral" : 1,
      "voteNo" : 1,
      "votePercent" : "78.57",
      "voteYes" : 5
   },
   {
      "artist" : "sa10/さ",
      "comment" : "ズレ　簡易版バナナマン",
      "level" : "9",
      "md5" : "2d034bffd18881fe6757706d6729eb33",
      "proposer" : "matsu",
      "proposerLr2id" : 127851,
      "sha256" : "6e129cd7120a2871867859ff3d097a7293f32fd540342e19f27f19677c28a249",
      "submission" : 714,
      "title" : "Drop! [SABOTHER]",
      "url" : "http://sound.jp/lobsak/bms.html",
      "url_diff" : "http://sabosabun.tank.jp/",
      "voteNeutral" : 1,
      "voteNo" : 1,
      "votePercent" : "78.57",
      "voteYes" : 5
   },
   {
      "artist" : "Alicia* / BGA:Fleeting Lovely/ 差分 赤い人",
      "comment" : "good",
      "level" : "7",
      "md5" : "2fb7b1615be8e37023a048679e4a5802",
      "proposer" : "Fendou",
      "proposerLr2id" : 128388,
      "sha256" : "72e493572a76da1a302e5e4daf87fe0bb146a26da5236d8aac884b86115d8ba6",
      "submission" : 706,
      "title" : "煌舞姫ベアトリクス [HARDEST]",
      "url" : "http://manbow.nothing.sh/event/event.cgi?action=More_def&num=238&event=83",
      "url_diff" : "http://akred.web.fc2.com/bmsfile/Beatrix-HARDEST_f.bms",
      "voteNeutral" : 1,
      "voteNo" : 0,
      "votePercent" : "94.44",
      "voteYes" : 8
   },
   {
      "artist" : "SHIKI / obj:BAECON",
      "comment" : "序盤の縦連に注意",
      "level" : "12",
      "md5" : "3f717790bfec084d8dd40a96a20b8d1c",
      "proposer" : "かに",
      "proposerLr2id" : 115381,
      "sha256" : "56fcda1311b5010264153697246ae8f19cc181943d130ab407a3bec91fb091b4",
      "submission" : 709,
      "title" : "CHASER [MANIAC]",
      "url" : "http://shiki2.sakura.ne.jp/",
      "url_diff" : "http://akred.web.fc2.com/baecon/chaserh7maniac.bme",
      "voteNeutral" : 4,
      "voteNo" : 0,
      "votePercent" : "66.67",
      "voteYes" : 2
   },
   {
      "artist" : "源屋feat.ユスラ obj:trainer",
      "comment" : "st0",
      "level" : "12",
      "md5" : "407c8e043a446c9dc99fc1ca97eb2fb5",
      "proposer" : "LUXURY♪",
      "proposerLr2id" : 23110,
      "sha256" : "438d308d441d44f3772bb77802d451b4f5c0f7c1052020cf0cb4a5a3efb1270c",
      "submission" : 703,
      "title" : "Magical Love Words [フィジカル横認識]",
      "url" : "http://manbow.nothing.sh/event/event.cgi?action=More_def&num=86&event=36",
      "url_diff" : "http://gnqg.rosx.net/upload/upload.cgi?get=02657",
      "voteNeutral" : 0,
      "voteNo" : 0,
      "votePercent" : 0,
      "voteYes" : 0
   },
   {
      "artist" : "Ym1024 obj:monaka",
      "comment" : "地力と少しのLN",
      "level" : "1",
      "md5" : "435dc5f3ba1e956124281e470a9a7071",
      "proposer" : "OXYGEN",
      "proposerLr2id" : 133294,
      "sha256" : "de71860a264d36efb1dd666b2afe396df923388377b0be4f51ea93449c7675ba",
      "submission" : 711,
      "title" : "April's Fantasy -Spring Bloom-",
      "url" : "http://yellowmapleleaf.com/bms/ym35_april_ogg.rar",
      "url_diff" : "https://bmscharteditorsgroup.wixsite.com/initialatoz",
      "voteNeutral" : 0,
      "voteNo" : 0,
      "votePercent" : "100.00",
      "voteYes" : 8
   },
   {
      "artist" : "LUNEの右手と悠里おねぇちゃんの左脚 /差分　赤い人",
      "comment" : "please kill me...",
      "level" : "12",
      "md5" : "51f9ce87e4a377f8009315568af297a2",
      "proposer" : "qtp13",
      "proposerLr2id" : 86559,
      "sha256" : "20cc5348c31b9552a459c0dd3913aeb790b388b3aa6e63a9adbde8d23981474d",
      "submission" : 708,
      "title" : "どうか私を殺して下さい [INFERNO]",
      "url" : "http://rin.s101.xrea.com/",
      "url_diff" : "http://akred.web.fc2.com/bmsfile/korosite-INFERNOf.bme",
      "voteNeutral" : 1,
      "voteNo" : 0,
      "votePercent" : "83.33",
      "voteYes" : 2
   },
   {
      "artist" : "L-Mys / M.H",
      "comment" : "THE 乱打 st0かも",
      "level" : "12",
      "md5" : "582c2715ca7ce2f0513fecdc3edeb5c4",
      "proposer" : "C4",
      "proposerLr2id" : 120385,
      "sha256" : "d93cf2e766444598bcfb0555d9a0d4c7c2ac3ad725813898644847681d686b22",
      "submission" : 725,
      "title" : "Lucifuge Rofocale [EX+]",
      "url" : "http://skydrive.live.com/?cid=ca7a5144414ec4ca&sc=documents&id=CA7A5144414EC4CA%21421",
      "url_diff" : "http://absolute.pv.land.to/bmsuploader.html",
      "voteNeutral" : 1,
      "voteNo" : 0,
      "votePercent" : "91.67",
      "voteYes" : 5
   },
   {
      "artist" : "mossari feat.TEA obj:SUZUKAZEΛ",
      "level" : "1",
      "md5" : "5f3baf7f14f8aa028ea542ddb24e5f26",
      "proposer" : "Haze*",
      "proposerLr2id" : 112076,
      "sha256" : "3034547411bbb2cebd5d76bac05a7552f763b4c4d0b39bf2153bfa131a13453b",
      "submission" : 723,
      "title" : "隣町の蜃気楼 [ZOI]",
      "url" : "http://manbow.nothing.sh/event/event.cgi?action=More_def&num=433&event=116",
      "url_diff" : "http://suzukazekuhare.web.fc2.com/suzukazelist.html",
      "voteNeutral" : 1,
      "voteNo" : 2,
      "votePercent" : "64.29",
      "voteYes" : 4
   },
   {
      "artist" : "Magic Mash Man / New Genuine Magicial Girl / obj:BAECON",
      "comment" : "名作",
      "level" : "12",
      "md5" : "676a1961313d51f9fef807cdc827f213",
      "proposer" : "かに",
      "proposerLr2id" : 115381,
      "sha256" : "35d9322be1363f65cede88cb7b16f23cd9be5a2739edf53fe05dab06944add15",
      "submission" : 712,
      "title" : "AXION [αχιον]",
      "url" : "http://manbow.nothing.sh/event/event.cgi?action=More_def&num=39&event=67",
      "url_diff" : "http://akred.web.fc2.com/baecon/axion_axion.bms",
      "voteNeutral" : 1,
      "voteNo" : 0,
      "votePercent" : "92.86",
      "voteYes" : 6
   },
   {
      "artist" : "azu/obj:uet",
      "level" : "1",
      "md5" : "71b650091137122b6f0c457dd927dea9",
      "proposer" : "Fendou",
      "proposerLr2id" : 128388,
      "sha256" : "a90f5a746c4d81635dd8fba4459e507ee85007c465dd7f171f967ce88c638a54",
      "submission" : 705,
      "title" : "Alicia Story (UETHER)",
      "url" : "http://manbow.nothing.sh/event/event.cgi?action=More_def&num=71&event=71",
      "url_diff" : "http://uetnosubarashikikusosabun.web.fc2.com/index.html",
      "voteNeutral" : 1,
      "voteNo" : 0,
      "votePercent" : "94.44",
      "voteYes" : 8
   },
   {
      "artist" : "sa10/差分 赤い人",
      "comment" : "Are you banana?",
      "level" : "5",
      "md5" : "85ff41c5e0d78d19d06507dbb16ba72f",
      "proposer" : "Haze*",
      "proposerLr2id" : 112076,
      "sha256" : "b861c54abe6cff9d156d1d3fc2feba02f36f49415241ebee996e2d0823bbdc35",
      "submission" : 724,
      "title" : "banana man [HARD]",
      "url" : "http://sound.jp/lobsak/",
      "url_diff" : "http://akred.web.fc2.com/bmsfile/bananaman-HARD.bms",
      "voteNeutral" : 2,
      "voteNo" : 2,
      "votePercent" : "72.73",
      "voteYes" : 7
   },
   {
      "artist" : "LiTaNia feat. RYL notes: MineC24",
      "comment" : "神ボーカル(?)",
      "level" : "2",
      "md5" : "874cbf72833dceb9de9aaab5a50c4a96",
      "proposer" : "MineC24",
      "proposerLr2id" : 84597,
      "sha256" : "209091e42c5c85b348a7f059a960ebafb0e8e3ec2eefb722a164ed5406d51d93",
      "submission" : 719,
      "title" : "Don't be Afraid [Cheer up!]",
      "url" : "https://onedrive.live.com/?cid=863934608D908CD0&id=863934608D908CD0%21105",
      "url_diff" : "https://www.dropbox.com/s/kxruiaa8thnkfb5/dontbeafraid_egs01.bme?dl=0",
      "voteNeutral" : 1,
      "voteNo" : 2,
      "votePercent" : "58.33",
      "voteYes" : 3
   },
   {
      "artist" : "カラフル・サウンズ・ポート/mov:むらしん / selene.",
      "comment" : "物量乱打, 高速階段",
      "level" : "7",
      "md5" : "8b46b0745658c595d343091a40dbda81",
      "proposer" : "nono22",
      "proposerLr2id" : 122934,
      "sha256" : "3e7065a9b3d91c432b9d060647d07379f088c772016e1ceedf4503059c3cd56b",
      "submission" : 737,
      "title" : "聖戦の輪舞 -Luna-",
      "url" : "http://manbow.nothing.sh/event/event.cgi?action=More_def&num=515&event=110",
      "url_diff" : "http://bmsselene.web.fc2.com/index.html",
      "voteNeutral" : 0,
      "voteNo" : 0,
      "votePercent" : "100.00",
      "voteYes" : 3
   },
   {
      "artist" : "Music : Lunatic Sounds / BGA : Photonskyto",
      "level" : "5",
      "md5" : "9a8e87868c57cedbf54167f3a826b141",
      "proposer" : "DK",
      "proposerLr2id" : 46697,
      "sha256" : "b346144f2075f08d474303bf7e93c9dc073348c4ec8b69985e0de7f810b3a23d",
      "submission" : 728,
      "title" : "DataErr0r [SP INSANE]",
      "url" : "http://manbow.nothing.sh/event/event.cgi?action=More_def&num=39&event=104",
      "url_diff" : "",
      "voteNeutral" : 0,
      "voteNo" : 1,
      "votePercent" : "80.00",
      "voteYes" : 4
   },
   {
      "artist" : "竜。 feat.結月ゆかり",
      "comment" : "KAWAII J-POP | BOFU2017、同時押し、中盤LNあり",
      "level" : "0",
      "md5" : "9e9db0e4203aebf050d0d6b5cb02299d",
      "proposer" : "ww",
      "proposerLr2id" : 147642,
      "sha256" : "5225baa0e28c4afa31b06b132aa99128e2afc92b92f65cca28a8be5b84fbd18d",
      "submission" : 707,
      "title" : "Re:Sound Sing Step -Another-",
      "url" : "http://manbow.nothing.sh/event/event.cgi?action=More_def&num=14&event=116",
      "url_diff" : "",
      "voteNeutral" : 0,
      "voteNo" : 0,
      "votePercent" : "100.00",
      "voteYes" : 10
   },
   {
      "artist" : "SP-#",
      "comment" : "高速乱打",
      "level" : "3",
      "md5" : "a096f87066726fa05f3254d7653f187d",
      "proposer" : "rat",
      "proposerLr2id" : 83454,
      "sha256" : "9f8f22746c5f8aa38999f9b3330ee5b5c14b173d96ef04055f80c01926873498",
      "submission" : 729,
      "title" : "tinnitus -7 another-",
      "url" : "https://onedrive.live.com/?cid=578814ACC2BD5A74&id=578814ACC2BD5A74!140",
      "url_diff" : "",
      "voteNeutral" : 4,
      "voteNo" : 1,
      "votePercent" : "70.00",
      "voteYes" : 5
   },
   {
      "artist" : "山蝙蝠ホールディングス movie : Y.A.B.tudidama / obj:NASA",
      "comment" : "局所の発狂有",
      "level" : "2",
      "md5" : "a5558c79adeaeccca3955e150304a139",
      "proposer" : "selene.",
      "proposerLr2id" : 84521,
      "sha256" : "7d1d8b0601c66d44e9c713ea176cdef6d3d1f753129b60bb8bc7653015ec1cae",
      "submission" : 686,
      "title" : "ほしぞら遊覧飛行 -under the milkyway-",
      "url" : "http://manbow.nothing.sh/event/event.cgi?action=More_def&event=104&num=222",
      "url_diff" : "http://gnqg.rosx.net/upload/",
      "voteNeutral" : 2,
      "voteNo" : 0,
      "votePercent" : "90.91",
      "voteYes" : 9
   },
   {
      "artist" : "Yu^ta Obj.Triforce",
      "comment" : "sl6~7",
      "level" : "6",
      "md5" : "a6f15937962bb5df6577869e60ca2fe6",
      "proposer" : "qtp13",
      "proposerLr2id" : 86559,
      "sha256" : "6133f359df7da46f448dd43812c33a13982301b1d66a1969b76e5c9c38a0cd26",
      "submission" : 710,
      "title" : "Love-Colored Look of the Sky [SSUT]",
      "url" : "http://manbow.nothing.sh/event/event.cgi?action=More_def&num=147&event=60",
      "url_diff" : "http://www.dropbox.com/s/hee18oafdlk40kl/_moeeuro_7triforce.bms?dl=0",
      "voteNeutral" : 0,
      "voteNo" : 0,
      "votePercent" : "100.00",
      "voteYes" : 4
   },
   {
      "artist" : "MALVA. vs. Venstant Illustration:Mare.S",
      "level" : "4",
      "md5" : "a8a6926a8d01f2df55de52babd59c7ad",
      "proposer" : "スノート",
      "proposerLr2id" : 86393,
      "sha256" : "e3e740765f9d1f424be4e8cf516ea9af77ee7b99dc50be64db68a7e3e305073d",
      "submission" : 732,
      "title" : "Spiritoso Killer [SP INSANE]",
      "url" : "http://manbow.nothing.sh/event/event.cgi?action=More_def&num=4&event=115",
      "url_diff" : "",
      "voteNeutral" : 1,
      "voteNo" : 0,
      "votePercent" : "92.86",
      "voteYes" : 6
   },
   {
      "artist" : "Gun-SEKI feat.那珂 / U",
      "comment" : "改とカッコカリの間 譜面属性的には改寄り",
      "level" : "7",
      "md5" : "aa2af9cff7b55399a051221d128d8699",
      "proposer" : "C4",
      "proposerLr2id" : 120385,
      "sha256" : "d2281ecafb865482b325814253566c8652ee31a6de54f667e0fb2f3f4cdfd1d0",
      "submission" : 726,
      "title" : "恋の2-4-11(BMS Edit) -改二-",
      "url" : "http://manbow.nothing.sh/event/event.cgi?action=More_def&num=74&event=96",
      "url_diff" : "http://www.geocities.jp/yjsnpi_kitanai_kusai_unko/index.html",
      "voteNeutral" : 1,
      "voteNo" : 1,
      "votePercent" : "81.25",
      "voteYes" : 6
   },
   {
      "artist" : "Maestro Zbigniew Obj.Triforce",
      "level" : "5",
      "md5" : "aaa979021c684b799e6b00943106b62c",
      "proposer" : "AXION",
      "proposerLr2id" : 37523,
      "sha256" : "956e9c0ccc926b2dc1e5077b83be78bf87ab314b6d6d0426e430f8e4f1fb6f2a",
      "submission" : 722,
      "title" : "Bravoooo!!!! [That's Right!]",
      "url" : "http://manbow.nothing.sh/event/event.cgi?action=More_def&num=347&event=104",
      "url_diff" : "http://www.dropbox.com/s/sex65vi8rtv8b31/Bravoooo%21%21%21%21%28triforce%29.bme?dl=0",
      "voteNeutral" : 4,
      "voteNo" : 2,
      "votePercent" : "50.00",
      "voteYes" : 2
   },
   {
      "artist" : "Blue-J",
      "comment" : "乱打,ラスト少し注意",
      "level" : "4",
      "md5" : "b0581c515b0e0e6d8cd51a17b251b67a",
      "proposer" : "Mayuzumy",
      "proposerLr2id" : 88804,
      "sha256" : "60a41f84316c404f2a5a9a3e82dc24b6fab961cf451a1a7d3f123fbddf95fe21",
      "submission" : 678,
      "title" : "FULL COMBO Pt.2 [FULL COMBO]",
      "url" : "https://drive.google.com/file/d/1g7vCOVyYhFJVEUeA2EjzadyuBKLmmrnQ/view?usp=sharing",
      "url_diff" : "",
      "voteNeutral" : 4,
      "voteNo" : 0,
      "votePercent" : "81.82",
      "voteYes" : 7
   },
   {
      "artist" : "saaa",
      "comment" : "saaa式乱打",
      "level" : "6",
      "md5" : "b6d071c80ab9bb84f3280264e4c616c3",
      "proposer" : "SANY",
      "proposerLr2id" : 128405,
      "sha256" : "844092b69c434504e234e8f813d00472f6b08f62b08fa32623b851f0e01de014",
      "submission" : 715,
      "title" : "INSANER [ANOTHER]",
      "url" : "http://manbow.nothing.sh/event/event.cgi?action=More_def&num=22&event=123",
      "url_diff" : "",
      "voteNeutral" : 1,
      "voteNo" : 1,
      "votePercent" : "81.25",
      "voteYes" : 6
   },
   {
      "artist" : "ああああ / in 幻の世界",
      "comment" : "適度なソフラン",
      "level" : "1",
      "md5" : "bcbdac0287dc4adad7e0103eb5120c46",
      "proposer" : "monaka",
      "proposerLr2id" : 93763,
      "sha256" : "478c162b16f8ac949de38b1ab6dcf86224a3dfddfb908af5edc2aac36048d425",
      "submission" : 696,
      "title" : "マージナル＊フロンティア [魔法世界へようこそ]",
      "url" : "http://manbow.nothing.sh/event/event.cgi?action=More_def&num=430&event=110",
      "url_diff" : "https://1drv.ms/x/s!Aoi5esJwIYCChk0BTx_U1KkswzSf",
      "voteNeutral" : 1,
      "voteNo" : 2,
      "votePercent" : "79.17",
      "voteYes" : 9
   },
   {
      "artist" : "Ark-Z  Illustration by 春雨 / obj:BAECON",
      "comment" : "トリル等",
      "level" : "7",
      "md5" : "c00300d042dd1c5b145f02106c81cb20",
      "proposer" : "matsu",
      "proposerLr2id" : 127851,
      "sha256" : "6a65a59e00c3cef7edb15bebd0e5bf9e1d67c1fdfd4e408db0a30f4e7cce1891",
      "submission" : 734,
      "title" : "Singing of Night birds [SKY]",
      "url" : "http://manbow.nothing.sh/event/event.cgi?action=More_def&num=37&event=92",
      "url_diff" : "http://flowermaster.web.fc2.com/kikaku/sabunsakusei.html",
      "voteNeutral" : 0,
      "voteNo" : 0,
      "votePercent" : "100.00",
      "voteYes" : 2
   },
   {
      "artist" : "LeaF",
      "comment" : "皿地帯無理でもクリア可能",
      "level" : "0",
      "md5" : "c26722df3891d23b67051bf9489af48b",
      "proposer" : "SANY",
      "proposerLr2id" : 128405,
      "sha256" : "44177b785cf968b2563e9fceb90f3015c8fa901e5997261bf5c8e2d9b0862b1e",
      "submission" : 718,
      "title" : "On The Floor -Baltimore Club mix- [ANOTHER]",
      "url" : "http://colosseo.nekokan.dyndns.info/c04_shuffle3/detail/view/50/",
      "url_diff" : "",
      "voteNeutral" : 2,
      "voteNo" : 7,
      "votePercent" : "33.33",
      "voteYes" : 3
   },
   {
      "artist" : "Negentropy Movie:Vogeln obj:sak",
      "comment" : "物量",
      "level" : "11",
      "md5" : "d7d5652bf8d7efad1fc26975a4615f1a",
      "proposer" : "姫川友紀",
      "proposerLr2id" : 125835,
      "sha256" : "fe726de74b6f1f958b241ba5c99fc1d745262fded629d6a860eaa3e98d1caa62",
      "submission" : 716,
      "title" : "ouroVoros [Judgment]",
      "url" : "http://manbow.nothing.sh/event/event.cgi?action=More_def&num=383&event=116",
      "url_diff" : "http://gnqg.rosx.net/upload/upload.cgi?get=01098",
      "voteNeutral" : 1,
      "voteNo" : 0,
      "votePercent" : "90.00",
      "voteYes" : 4
   },
   {
      "artist" : "shimizushi illust:a.a / obj:DJ.END",
      "comment" : "sl4-5 | A-1 Climax 8th、乱打、中盤発狂、連打のラスト殺し",
      "level" : "5",
      "md5" : "dc569990b2806be2189793d207b00682",
      "proposer" : "ww",
      "proposerLr2id" : 147642,
      "sha256" : "c71c56c7ac747d3780f033ac4858729e76300aafe94b1619ad3929f4a30e8ca7",
      "submission" : 704,
      "title" : "SATSUKI [White Another]",
      "url" : "http://manbow.nothing.sh/event/event.cgi?action=More_def&num=62&event=121",
      "url_diff" : "",
      "voteNeutral" : 2,
      "voteNo" : 1,
      "votePercent" : "66.67",
      "voteYes" : 3
   },
   {
      "artist" : "hugepulse obj.qfeileadh",
      "comment" : "軸、乱打、高速",
      "level" : "12",
      "md5" : "dfcfdc70a61290f57b768ef1a2ad6aac",
      "proposer" : "rat",
      "proposerLr2id" : 83454,
      "sha256" : "afd38186e7221124c7e774e599266b2a17b95f0a78409aa86f2d1451daa9b7f1",
      "submission" : 727,
      "title" : "クォークの海を泳いで [SP NEUTRINO]",
      "url" : "http://manbow.nothing.sh/event/event.cgi?action=More_def&num=28&event=121",
      "url_diff" : "",
      "voteNeutral" : 1,
      "voteNo" : 0,
      "votePercent" : "87.50",
      "voteYes" : 3
   },
   {
      "artist" : "翡乃イスカ",
      "comment" : "高速乱打、皿、ラスト、縦連",
      "level" : "7",
      "md5" : "eb01a20f9358c2fb0843579fdfaa087e",
      "proposer" : "Triforce",
      "proposerLr2id" : 18553,
      "sha256" : "24666bab553f5675edf77b1c313fd613a5b1003e7ec6c275a9f289cb343684b7",
      "submission" : 731,
      "title" : "#be_fortunate [Futabather]",
      "url" : "http://manbow.nothing.sh/event/event.cgi?action=More_def&num=387&event=123",
      "url_diff" : "http://gnqg.rosx.net/upload/upload.cgi?get=02745",
      "voteNeutral" : 2,
      "voteNo" : 3,
      "votePercent" : "42.86",
      "voteYes" : 2
   },
   {
      "artist" : "LSD / obj:K-SPIN",
      "comment" : "GENOCIDE★5 微縦連、ディレイ入門",
      "level" : "3",
      "md5" : "eb4944ba424cd3f220b368fdaec14cd3",
      "proposer" : "なさ式",
      "proposerLr2id" : 108918,
      "sha256" : "2492bfa9d0b090cef2b23b84e171397c6183dee9e1a22c54621dd3801172afd4",
      "submission" : 697,
      "title" : "square and breaks -collapse-",
      "url" : "http://manbow.nothing.sh/event/event.cgi?action=More_def&num=307&event=104",
      "url_diff" : "http://kspinbms.web.fc2.com/insane.html",
      "voteNeutral" : 4,
      "voteNo" : 4,
      "votePercent" : "62.50",
      "voteYes" : 8
   },
   {
      "artist" : "KAH BGA:自動車 原付 / illust:手鞠鈴 / obj:SUZUKAZEΛ",
      "comment" : "5~6?皿ある",
      "level" : "5",
      "md5" : "ee9cfc1bc594438b1c3ddd10b4ba7198",
      "proposer" : "MineC24",
      "proposerLr2id" : 84597,
      "sha256" : "b93576fd2b7bf5b6023622effc14b2808559757c717314d8c9ef2dea9ab985e9",
      "submission" : 717,
      "title" : "energy trixxx [ZOI]",
      "url" : "http://manbow.nothing.sh/event/event.cgi?action=More_def&num=72&event=123",
      "url_diff" : "http://suzukazekuhare.web.fc2.com/suzukazelist.html",
      "voteNeutral" : 1,
      "voteNo" : 4,
      "votePercent" : "35.71",
      "voteYes" : 2
   },
   {
      "artist" : "梅干茶漬け/ obj:赤い人",
      "comment" : "",
      "level" : "6",
      "md5" : "f6298076c6f7b8661c6c72575fca1ec6",
      "proposer" : "椒図",
      "proposerLr2id" : 124809,
      "sha256" : "d9ae5d752b3a4edaf7268c4dfcbf535360d07340a1f5eefe01dc76f064875c1e",
      "submission" : 721,
      "title" : "Lollipop☆driveR [HARDEST]",
      "url" : "http://manbow.nothing.sh/event/event.cgi?action=More_def&num=196&event=104",
      "url_diff" : "http://akred.web.fc2.com/bmsfile/_Lollopop-driveR-HARDEST.bms",
      "voteNeutral" : 0,
      "voteNo" : 0,
      "votePercent" : "100.00",
      "voteYes" : 5
   },
   {
      "artist" : "Sound piercer vs. Iriss obj.Lapis",
      "comment" : "复合、乱打",
      "level" : "5",
      "md5" : "f94e4a5f13263fdb5ee4aa74e0856b47",
      "proposer" : "椒図",
      "proposerLr2id" : 124809,
      "sha256" : "c3017128c7c0e06e2d3506d6b749071cea520c4901bb40eebc0bf528c387e34f",
      "submission" : 720,
      "title" : "BOUNCE THE TECH [M4KE S0M3 N01SE]",
      "url" : "http://k-bms.com/party_pabat/party2017.jsp?board_num=17&num=27",
      "url_diff" : "http://lapisbms.web.fc2.com/",
      "voteNeutral" : 3,
      "voteNo" : 0,
      "votePercent" : "70.00",
      "voteYes" : 2
   }
]
